Metadata-Version: 1.2
Name: django-dbconn-retry-python27
Version: 0.1.6
Summary: Patch Django to retry a database connection first before failing.
Home-page: https://github.com/jdelic/django-dbconn-retry/
Author: Jonas Maurus (@jdelic) (original), Scott Baker (python2.7 port)
Author-email: jonas-dbconn-retry@gopythongo.com, scottb@opennetworking.org
Maintainer: GoPythonGo.com
Maintainer-email: info@gopythongo.com, scottb@opennetworking.org
License: UNKNOWN
Platform: UNKNOWN
Classifier: Development Status :: 4 - Beta
Classifier: Intended Audience :: Developers
Classifier: Intended Audience :: System Administrators
Classifier: License :: OSI Approved :: BSD License
Classifier: Operating System :: POSIX
